{"make":"TOYOTA","model":"YARIS","make_slug":"toyota","model_slug":"yaris","first_reg_year":2020,"fuels":[],"co2_panel":[],"recalls":[],"mot_curve":[{"age":3,"tests":null,"pass_rate":0.891,"mileage":{"p50":20222.0,"p75":28884.0,"p90":38314.0},"fail_mix":[]},{"age":4,"tests":null,"pass_rate":0.88,"mileage":{"p50":21626.0,"p75":30394.0,"p90":38883.0},"fail_mix":[]}],"meta":{"source":"DVSA anonymised MOT results & failure items (OGL v3.0); DVSA Recalls; VCA CO₂/MPG; GOV.UK VED","version":"weekly"}}