{"make":"NISSAN","model":"CABSTAR","make_slug":"nissan","model_slug":"cabstar","first_reg_year":2019,"fuels":[],"co2_panel":[],"recalls":[],"mot_curve":[{"age":4,"tests":null,"pass_rate":0.681,"mileage":{"p50":45768.0,"p75":78145.0,"p90":119513.0},"fail_mix":[]},{"age":5,"tests":null,"pass_rate":0.542,"mileage":{"p50":49659.0,"p75":51228.0,"p90":67018.0},"fail_mix":[]}],"meta":{"source":"DVSA anonymised MOT results & failure items (OGL v3.0); DVSA Recalls; VCA CO₂/MPG; GOV.UK VED","version":"weekly"}}