{"make":"TOYOTA","model":"PRIUS","make_slug":"toyota","model_slug":"prius","first_reg_year":2022,"fuels":[],"co2_panel":[],"recalls":[],"mot_curve":[{"age":1,"tests":null,"pass_rate":0.964,"mileage":{"p50":31608.0,"p75":50117.0,"p90":72852.0},"fail_mix":[]},{"age":2,"tests":null,"pass_rate":0.889,"mileage":{"p50":57298.0,"p75":98761.0,"p90":106605.0},"fail_mix":[]}],"meta":{"source":"DVSA anonymised MOT results & failure items (OGL v3.0); DVSA Recalls; VCA CO₂/MPG; GOV.UK VED","version":"weekly"}}