{"make":"VOLKSWAGEN","model":"SCIROCCO","make_slug":"volkswagen","model_slug":"scirocco","first_reg_year":1986,"fuels":[],"co2_panel":[],"recalls":[],"mot_curve":[{"age":37,"tests":null,"pass_rate":0.75,"mileage":{"p50":107521.0,"p75":127111.0,"p90":127111.0},"fail_mix":[]},{"age":38,"tests":null,"pass_rate":0.5,"mileage":{"p50":85382.0,"p75":85383.0,"p90":85383.0},"fail_mix":[]}],"meta":{"source":"DVSA anonymised MOT results & failure items (OGL v3.0); DVSA Recalls; VCA CO₂/MPG; GOV.UK VED","version":"weekly"}}