{"make":"HONDA","model":"CRF 1100 D-L","make_slug":"honda","model_slug":"crf-1100-d-l","first_reg_year":2020,"fuels":[],"co2_panel":[],"recalls":[],"mot_curve":[{"age":3,"tests":null,"pass_rate":1.0,"mileage":{"p50":6929.0,"p75":12645.0,"p90":13755.0},"fail_mix":[]},{"age":4,"tests":null,"pass_rate":0.8,"mileage":{"p50":8002.0,"p75":17657.0,"p90":17657.0},"fail_mix":[]}],"meta":{"source":"DVSA anonymised MOT results & failure items (OGL v3.0); DVSA Recalls; VCA CO₂/MPG; GOV.UK VED","version":"weekly"}}