{"make":"ALFA ROMEO","model":"GIULIETTA","make_slug":"alfa-romeo","model_slug":"giulietta","first_reg_year":2017,"fuels":[],"co2_panel":[],"recalls":[],"mot_curve":[{"age":6,"tests":null,"pass_rate":0.797,"mileage":{"p50":50074.0,"p75":65484.0,"p90":79711.0},"fail_mix":[]},{"age":7,"tests":null,"pass_rate":0.8,"mileage":{"p50":48265.0,"p75":67496.0,"p90":82997.0},"fail_mix":[]}],"meta":{"source":"DVSA anonymised MOT results & failure items (OGL v3.0); DVSA Recalls; VCA CO₂/MPG; GOV.UK VED","version":"weekly"}}