{"make":"YAMAHA","model":"YP250","make_slug":"yamaha","model_slug":"yp250","first_reg_year":2013,"fuels":[],"co2_panel":[],"recalls":[],"mot_curve":[{"age":10,"tests":null,"pass_rate":1.0,"mileage":{"p50":19035.0,"p75":19035.0,"p90":19035.0},"fail_mix":[]},{"age":11,"tests":null,"pass_rate":1.0,"mileage":{"p50":13618.0,"p75":16863.0,"p90":18810.0},"fail_mix":[]}],"meta":{"source":"DVSA anonymised MOT results & failure items (OGL v3.0); DVSA Recalls; VCA CO₂/MPG; GOV.UK VED","version":"weekly"}}