{"make":"BENTLEY","model":"CONTINENTAL","make_slug":"bentley","model_slug":"continental","first_reg_year":2010,"fuels":[],"co2_panel":[],"recalls":[],"mot_curve":[{"age":13,"tests":null,"pass_rate":0.978,"mileage":{"p50":49205.0,"p75":61651.0,"p90":65440.0},"fail_mix":[]},{"age":14,"tests":null,"pass_rate":1.0,"mileage":{"p50":41806.0,"p75":64500.0,"p90":70072.0},"fail_mix":[]}],"meta":{"source":"DVSA anonymised MOT results & failure items (OGL v3.0); DVSA Recalls; VCA CO₂/MPG; GOV.UK VED","version":"weekly"}}