{"make":"MAZDA","model":"BONGO`","make_slug":"mazda","model_slug":"bongo","first_reg_year":1997,"fuels":[],"co2_panel":[],"recalls":[],"mot_curve":[{"age":26,"tests":null,"pass_rate":0.732,"mileage":{"p50":148533.0,"p75":211360.0,"p90":313406.0},"fail_mix":[]},{"age":26,"tests":null,"pass_rate":1.0,"mileage":{"p50":111563.0,"p75":111563.0,"p90":111563.0},"fail_mix":[]},{"age":27,"tests":null,"pass_rate":0.655,"mileage":{"p50":161203.0,"p75":211788.0,"p90":254975.0},"fail_mix":[]}],"meta":{"source":"DVSA anonymised MOT results & failure items (OGL v3.0); DVSA Recalls; VCA CO₂/MPG; GOV.UK VED","version":"weekly"}}