{"make":"LEXUS","model":"SC430","make_slug":"lexus","model_slug":"sc430","first_reg_year":2007,"fuels":[],"co2_panel":[],"recalls":[],"mot_curve":[{"age":16,"tests":null,"pass_rate":0.895,"mileage":{"p50":51238.0,"p75":67673.0,"p90":89954.0},"fail_mix":[]},{"age":17,"tests":null,"pass_rate":1.0,"mileage":{"p50":42640.0,"p75":42640.0,"p90":42640.0},"fail_mix":[]}],"meta":{"source":"DVSA anonymised MOT results & failure items (OGL v3.0); DVSA Recalls; VCA CO₂/MPG; GOV.UK VED","version":"weekly"}}