{"make":"IVECO","model":"DAILY","make_slug":"iveco","model_slug":"daily","first_reg_year":2009,"fuels":[],"co2_panel":[],"recalls":[],"mot_curve":[{"age":14,"tests":null,"pass_rate":0.594,"mileage":{"p50":115972.0,"p75":159553.0,"p90":226914.0},"fail_mix":[]},{"age":15,"tests":null,"pass_rate":0.6,"mileage":{"p50":153327.0,"p75":178771.0,"p90":294293.0},"fail_mix":[]}],"meta":{"source":"DVSA anonymised MOT results & failure items (OGL v3.0); DVSA Recalls; VCA CO₂/MPG; GOV.UK VED","version":"weekly"}}