{"make":"RENAULT","model":"SCENIC","make_slug":"renault","model_slug":"scenic","first_reg_year":2003,"fuels":[],"co2_panel":[],"recalls":[],"mot_curve":[{"age":20,"tests":null,"pass_rate":0.644,"mileage":{"p50":109033.0,"p75":133229.0,"p90":149797.0},"fail_mix":[]},{"age":21,"tests":null,"pass_rate":0.667,"mileage":{"p50":116146.0,"p75":123891.0,"p90":128488.0},"fail_mix":[]}],"meta":{"source":"DVSA anonymised MOT results & failure items (OGL v3.0); DVSA Recalls; VCA CO₂/MPG; GOV.UK VED","version":"weekly"}}