{"make":"VAUXHALL","model":"ASTRA SRI NAV TURBO D","make_slug":"vauxhall","model_slug":"astra-sri-nav-turbo-d","first_reg_year":2020,"fuels":[],"co2_panel":[],"recalls":[],"mot_curve":[{"age":3,"tests":null,"pass_rate":0.5,"mileage":{"p50":47080.0,"p75":52162.0,"p90":58772.0},"fail_mix":[]},{"age":4,"tests":null,"pass_rate":1.0,"mileage":{"p50":24268.0,"p75":24268.0,"p90":24268.0},"fail_mix":[]}],"meta":{"source":"DVSA anonymised MOT results & failure items (OGL v3.0); DVSA Recalls; VCA CO₂/MPG; GOV.UK VED","version":"weekly"}}