{"make":"FIAT","model":"SEDICI","make_slug":"fiat","model_slug":"sedici","first_reg_year":2007,"fuels":[],"co2_panel":[],"recalls":[],"mot_curve":[{"age":16,"tests":null,"pass_rate":0.587,"mileage":{"p50":110189.0,"p75":126740.0,"p90":155102.0},"fail_mix":[]},{"age":17,"tests":null,"pass_rate":1.0,"mileage":{"p50":104769.0,"p75":127273.0,"p90":133877.0},"fail_mix":[]}],"meta":{"source":"DVSA anonymised MOT results & failure items (OGL v3.0); DVSA Recalls; VCA CO₂/MPG; GOV.UK VED","version":"weekly"}}