{"make":"KTM","model":"790 ADVENTURE R 19","make_slug":"ktm","model_slug":"790-adventure-r-19","first_reg_year":2019,"fuels":[],"co2_panel":[],"recalls":[],"mot_curve":[{"age":4,"tests":null,"pass_rate":0.6,"mileage":{"p50":14233.0,"p75":15646.0,"p90":15646.0},"fail_mix":[]},{"age":5,"tests":null,"pass_rate":1.0,"mileage":{"p50":10375.0,"p75":11176.0,"p90":11176.0},"fail_mix":[]}],"meta":{"source":"DVSA anonymised MOT results & failure items (OGL v3.0); DVSA Recalls; VCA CO₂/MPG; GOV.UK VED","version":"weekly"}}