{"make":"CITROEN","model":"DISPATCH","make_slug":"citroen","model_slug":"dispatch","first_reg_year":2002,"fuels":[],"co2_panel":[],"recalls":[],"mot_curve":[{"age":21,"tests":null,"pass_rate":0.806,"mileage":{"p50":124085.0,"p75":149925.0,"p90":155914.0},"fail_mix":[]},{"age":22,"tests":null,"pass_rate":0.571,"mileage":{"p50":101088.0,"p75":113982.0,"p90":121719.0},"fail_mix":[]}],"meta":{"source":"DVSA anonymised MOT results & failure items (OGL v3.0); DVSA Recalls; VCA CO₂/MPG; GOV.UK VED","version":"weekly"}}