{"make":"MERCEDES-BENZ","model":"SL","make_slug":"mercedes-benz","model_slug":"sl","first_reg_year":1998,"fuels":[],"co2_panel":[],"recalls":[],"mot_curve":[{"age":25,"tests":null,"pass_rate":0.808,"mileage":{"p50":87537.0,"p75":112198.0,"p90":138369.0},"fail_mix":[]},{"age":26,"tests":null,"pass_rate":0.92,"mileage":{"p50":101309.0,"p75":107703.0,"p90":124386.0},"fail_mix":[]}],"meta":{"source":"DVSA anonymised MOT results & failure items (OGL v3.0); DVSA Recalls; VCA CO₂/MPG; GOV.UK VED","version":"weekly"}}