{"make":"TOYOTA","model":"COROLLA EXCEL HEV CVT","make_slug":"toyota","model_slug":"corolla-excel-hev-cvt","first_reg_year":2020,"fuels":[],"co2_panel":[],"recalls":[],"mot_curve":[{"age":3,"tests":null,"pass_rate":0.901,"mileage":{"p50":27423.0,"p75":36276.0,"p90":55719.0},"fail_mix":[]},{"age":4,"tests":null,"pass_rate":0.867,"mileage":{"p50":33660.0,"p75":47207.0,"p90":74893.0},"fail_mix":[]}],"meta":{"source":"DVSA anonymised MOT results & failure items (OGL v3.0); DVSA Recalls; VCA CO₂/MPG; GOV.UK VED","version":"weekly"}}