{"make":"FIAT","model":"DOBLO","make_slug":"fiat","model_slug":"doblo","first_reg_year":2010,"fuels":[],"co2_panel":[],"recalls":[],"mot_curve":[{"age":13,"tests":null,"pass_rate":0.706,"mileage":{"p50":92902.0,"p75":125172.0,"p90":153347.0},"fail_mix":[]},{"age":14,"tests":null,"pass_rate":0.7,"mileage":{"p50":84928.0,"p75":97670.0,"p90":138587.0},"fail_mix":[]}],"meta":{"source":"DVSA anonymised MOT results & failure items (OGL v3.0); DVSA Recalls; VCA CO₂/MPG; GOV.UK VED","version":"weekly"}}