{"make":"LAND ROVER","model":"FREELANDER","make_slug":"land-rover","model_slug":"freelander","first_reg_year":2011,"fuels":[],"co2_panel":[],"recalls":[],"mot_curve":[{"age":12,"tests":null,"pass_rate":0.79,"mileage":{"p50":111312.0,"p75":134558.0,"p90":161876.0},"fail_mix":[]},{"age":13,"tests":null,"pass_rate":0.781,"mileage":{"p50":117263.0,"p75":145342.0,"p90":163659.0},"fail_mix":[]}],"meta":{"source":"DVSA anonymised MOT results & failure items (OGL v3.0); DVSA Recalls; VCA CO₂/MPG; GOV.UK VED","version":"weekly"}}