{"make":"HYUNDAI","model":"I20","make_slug":"hyundai","model_slug":"i20","first_reg_year":2016,"fuels":[],"co2_panel":[],"recalls":[],"mot_curve":[{"age":7,"tests":null,"pass_rate":0.849,"mileage":{"p50":48934.0,"p75":62565.0,"p90":79257.0},"fail_mix":[]},{"age":8,"tests":null,"pass_rate":0.861,"mileage":{"p50":50494.0,"p75":77999.0,"p90":97433.0},"fail_mix":[]}],"meta":{"source":"DVSA anonymised MOT results & failure items (OGL v3.0); DVSA Recalls; VCA CO₂/MPG; GOV.UK VED","version":"weekly"}}