{"make":"JEEP","model":"COMPASS","make_slug":"jeep","model_slug":"compass","first_reg_year":2021,"fuels":[],"co2_panel":[],"recalls":[],"mot_curve":[{"age":2,"tests":null,"pass_rate":0.815,"mileage":{"p50":22606.0,"p75":28214.0,"p90":32101.0},"fail_mix":[]},{"age":3,"tests":null,"pass_rate":0.938,"mileage":{"p50":23812.0,"p75":29248.0,"p90":35800.0},"fail_mix":[]}],"meta":{"source":"DVSA anonymised MOT results & failure items (OGL v3.0); DVSA Recalls; VCA CO₂/MPG; GOV.UK VED","version":"weekly"}}