{"make":"KAWASAKI","model":"ZZR1400","make_slug":"kawasaki","model_slug":"zzr1400","first_reg_year":2007,"fuels":[],"co2_panel":[],"recalls":[],"mot_curve":[{"age":16,"tests":null,"pass_rate":0.875,"mileage":{"p50":41136.0,"p75":53691.0,"p90":64540.0},"fail_mix":[]},{"age":17,"tests":null,"pass_rate":1.0,"mileage":{"p50":25953.0,"p75":25953.0,"p90":25953.0},"fail_mix":[]}],"meta":{"source":"DVSA anonymised MOT results & failure items (OGL v3.0); DVSA Recalls; VCA CO₂/MPG; GOV.UK VED","version":"weekly"}}