{"make":"KAWASAKI","model":"ZX6R","make_slug":"kawasaki","model_slug":"zx6r","first_reg_year":2002,"fuels":[],"co2_panel":[],"recalls":[],"mot_curve":[{"age":21,"tests":null,"pass_rate":1.0,"mileage":{"p50":26575.0,"p75":29174.0,"p90":30733.0},"fail_mix":[]},{"age":22,"tests":null,"pass_rate":1.0,"mileage":{"p50":38751.0,"p75":38751.0,"p90":38751.0},"fail_mix":[]}],"meta":{"source":"DVSA anonymised MOT results & failure items (OGL v3.0); DVSA Recalls; VCA CO₂/MPG; GOV.UK VED","version":"weekly"}}