{"make":"PEUGEOT","model":"208 ALLURE PURETECH S/S AUTO","make_slug":"peugeot","model_slug":"208-allure-puretech-s-s-auto","first_reg_year":2021,"fuels":[],"co2_panel":[],"recalls":[],"mot_curve":[{"age":2,"tests":null,"pass_rate":0.893,"mileage":{"p50":14868.0,"p75":20638.0,"p90":38533.0},"fail_mix":[]},{"age":3,"tests":null,"pass_rate":1.0,"mileage":{"p50":29050.0,"p75":32882.0,"p90":35181.0},"fail_mix":[]}],"meta":{"source":"DVSA anonymised MOT results & failure items (OGL v3.0); DVSA Recalls; VCA CO₂/MPG; GOV.UK VED","version":"weekly"}}