{"make":"RENAULT","model":"TRAFIC","make_slug":"renault","model_slug":"trafic","first_reg_year":1995,"fuels":[],"co2_panel":[],"recalls":[],"mot_curve":[{"age":28,"tests":null,"pass_rate":0.69,"mileage":{"p50":72834.0,"p75":78295.0,"p90":104595.0},"fail_mix":[]},{"age":29,"tests":null,"pass_rate":1.0,"mileage":{"p50":57456.0,"p75":159882.0,"p90":159882.0},"fail_mix":[]}],"meta":{"source":"DVSA anonymised MOT results & failure items (OGL v3.0); DVSA Recalls; VCA CO₂/MPG; GOV.UK VED","version":"weekly"}}