{"make":"RENAULT","model":"TRAFIC","make_slug":"renault","model_slug":"trafic","first_reg_year":2007,"fuels":[],"co2_panel":[],"recalls":[],"mot_curve":[{"age":16,"tests":null,"pass_rate":0.627,"mileage":{"p50":154367.0,"p75":189638.0,"p90":222312.0},"fail_mix":[]},{"age":17,"tests":null,"pass_rate":0.712,"mileage":{"p50":138842.0,"p75":161124.0,"p90":198520.0},"fail_mix":[]}],"meta":{"source":"DVSA anonymised MOT results & failure items (OGL v3.0); DVSA Recalls; VCA CO₂/MPG; GOV.UK VED","version":"weekly"}}