{"make":"BMW","model":"3 SERIES","make_slug":"bmw","model_slug":"3-series","first_reg_year":1986,"fuels":[],"co2_panel":[],"recalls":[],"mot_curve":[{"age":37,"tests":null,"pass_rate":1.0,"mileage":{"p50":84324.0,"p75":123656.0,"p90":134454.0},"fail_mix":[]},{"age":38,"tests":null,"pass_rate":1.0,"mileage":{"p50":53091.0,"p75":53091.0,"p90":53091.0},"fail_mix":[]}],"meta":{"source":"DVSA anonymised MOT results & failure items (OGL v3.0); DVSA Recalls; VCA CO₂/MPG; GOV.UK VED","version":"weekly"}}