{"make":"MERCEDES-BENZ","model":"AMG C 43 NIGHT ED PREM + 4M A","make_slug":"mercedes-benz","model_slug":"amg-c-43-night-ed-prem-4m-a","first_reg_year":2021,"fuels":[],"co2_panel":[],"recalls":[],"mot_curve":[{"age":2,"tests":null,"pass_rate":0.882,"mileage":{"p50":21923.0,"p75":27608.0,"p90":32116.0},"fail_mix":[]},{"age":3,"tests":null,"pass_rate":0.897,"mileage":{"p50":28014.0,"p75":31289.0,"p90":43048.0},"fail_mix":[]}],"meta":{"source":"DVSA anonymised MOT results & failure items (OGL v3.0); DVSA Recalls; VCA CO₂/MPG; GOV.UK VED","version":"weekly"}}