{"make":"ROYAL ALLOY","model":"GT 200 LC","make_slug":"royal-alloy","model_slug":"gt-200-lc","first_reg_year":2019,"fuels":[],"co2_panel":[],"recalls":[],"mot_curve":[{"age":4,"tests":null,"pass_rate":1.0,"mileage":{"p50":1386.0,"p75":1386.0,"p90":1386.0},"fail_mix":[]},{"age":5,"tests":null,"pass_rate":1.0,"mileage":{"p50":5039.0,"p75":5039.0,"p90":5039.0},"fail_mix":[]}],"meta":{"source":"DVSA anonymised MOT results & failure items (OGL v3.0); DVSA Recalls; VCA CO₂/MPG; GOV.UK VED","version":"weekly"}}