{"make":"TESLA","model":"MODEL Y RWD","make_slug":"tesla","model_slug":"model-y-rwd","first_reg_year":2023,"fuels":[],"co2_panel":[],"recalls":[],"mot_curve":[{"age":0,"tests":null,"pass_rate":0.868,"mileage":{"p50":31970.0,"p75":38219.0,"p90":47603.0},"fail_mix":[]},{"age":1,"tests":null,"pass_rate":0.929,"mileage":{"p50":23820.0,"p75":39120.0,"p90":49030.0},"fail_mix":[]}],"meta":{"source":"DVSA anonymised MOT results & failure items (OGL v3.0); DVSA Recalls; VCA CO₂/MPG; GOV.UK VED","version":"weekly"}}