{"make":"MAZDA","model":"BONGO/FRIENDEE","make_slug":"mazda","model_slug":"bongo-friendee","first_reg_year":2016,"fuels":[],"co2_panel":[],"recalls":[],"mot_curve":[{"age":7,"tests":null,"pass_rate":0.5,"mileage":{"p50":205108.0,"p75":205108.0,"p90":205108.0},"fail_mix":[]},{"age":8,"tests":null,"pass_rate":0.5,"mileage":{"p50":100433.0,"p75":100434.0,"p90":100435.0},"fail_mix":[]}],"meta":{"source":"DVSA anonymised MOT results & failure items (OGL v3.0); DVSA Recalls; VCA CO₂/MPG; GOV.UK VED","version":"weekly"}}