{"make":"CITROEN","model":"C4 GRAND STOURER FEEL+ PTCH SS","make_slug":"citroen","model_slug":"c4-grand-stourer-feel-ptch-ss","first_reg_year":2020,"fuels":[],"co2_panel":[],"recalls":[],"mot_curve":[{"age":3,"tests":null,"pass_rate":0.878,"mileage":{"p50":35480.0,"p75":41475.0,"p90":59556.0},"fail_mix":[]},{"age":4,"tests":null,"pass_rate":0.818,"mileage":{"p50":37118.0,"p75":42184.0,"p90":42186.0},"fail_mix":[]}],"meta":{"source":"DVSA anonymised MOT results & failure items (OGL v3.0); DVSA Recalls; VCA CO₂/MPG; GOV.UK VED","version":"weekly"}}