{"make":"MERCEDES-BENZ","model":"A 250 AMG LINE PREMIUM + E A","make_slug":"mercedes-benz","model_slug":"a-250-amg-line-premium-e-a","first_reg_year":2021,"fuels":[],"co2_panel":[],"recalls":[],"mot_curve":[{"age":2,"tests":null,"pass_rate":0.95,"mileage":{"p50":24849.0,"p75":33926.0,"p90":47833.0},"fail_mix":[]},{"age":3,"tests":null,"pass_rate":0.714,"mileage":{"p50":20207.0,"p75":43757.0,"p90":61312.0},"fail_mix":[]}],"meta":{"source":"DVSA anonymised MOT results & failure items (OGL v3.0); DVSA Recalls; VCA CO₂/MPG; GOV.UK VED","version":"weekly"}}