{"make":"JAGUAR","model":"X-TYPE","make_slug":"jaguar","model_slug":"x-type","first_reg_year":2003,"fuels":[],"co2_panel":[],"recalls":[],"mot_curve":[{"age":20,"tests":null,"pass_rate":0.667,"mileage":{"p50":92291.0,"p75":106584.0,"p90":129054.0},"fail_mix":[]},{"age":21,"tests":null,"pass_rate":0.569,"mileage":{"p50":73297.0,"p75":112527.0,"p90":132262.0},"fail_mix":[]}],"meta":{"source":"DVSA anonymised MOT results & failure items (OGL v3.0); DVSA Recalls; VCA CO₂/MPG; GOV.UK VED","version":"weekly"}}