{"make":"MERCEDES-BENZ","model":"230","make_slug":"mercedes-benz","model_slug":"230","first_reg_year":1983,"fuels":[],"co2_panel":[],"recalls":[],"mot_curve":[{"age":40,"tests":null,"pass_rate":0.875,"mileage":{"p50":109860.0,"p75":128451.0,"p90":130961.0},"fail_mix":[]},{"age":41,"tests":null,"pass_rate":1.0,"mileage":{"p50":130961.0,"p75":130961.0,"p90":130961.0},"fail_mix":[]}],"meta":{"source":"DVSA anonymised MOT results & failure items (OGL v3.0); DVSA Recalls; VCA CO₂/MPG; GOV.UK VED","version":"weekly"}}