{"make":"SUZUKI","model":"GSXR 600 K6","make_slug":"suzuki","model_slug":"gsxr-600-k6","first_reg_year":2006,"fuels":[],"co2_panel":[],"recalls":[],"mot_curve":[{"age":17,"tests":null,"pass_rate":0.931,"mileage":{"p50":21190.0,"p75":28788.0,"p90":33356.0},"fail_mix":[]},{"age":18,"tests":null,"pass_rate":1.0,"mileage":{"p50":25424.0,"p75":25424.0,"p90":25424.0},"fail_mix":[]}],"meta":{"source":"DVSA anonymised MOT results & failure items (OGL v3.0); DVSA Recalls; VCA CO₂/MPG; GOV.UK VED","version":"weekly"}}