{"make":"SKODA","model":"SUPERB SE L TSI S-A","make_slug":"skoda","model_slug":"superb-se-l-tsi-s-a","first_reg_year":2020,"fuels":[],"co2_panel":[],"recalls":[],"mot_curve":[{"age":3,"tests":null,"pass_rate":1.0,"mileage":{"p50":25837.0,"p75":31066.0,"p90":42180.0},"fail_mix":[]},{"age":4,"tests":null,"pass_rate":0.889,"mileage":{"p50":20990.0,"p75":46346.0,"p90":46346.0},"fail_mix":[]}],"meta":{"source":"DVSA anonymised MOT results & failure items (OGL v3.0); DVSA Recalls; VCA CO₂/MPG; GOV.UK VED","version":"weekly"}}