{"make":"VAUXHALL","model":"CORSA","make_slug":"vauxhall","model_slug":"corsa","first_reg_year":1998,"fuels":[],"co2_panel":[],"recalls":[],"mot_curve":[{"age":25,"tests":null,"pass_rate":0.684,"mileage":{"p50":74433.0,"p75":102417.0,"p90":115450.0},"fail_mix":[]},{"age":26,"tests":null,"pass_rate":0.72,"mileage":{"p50":87475.0,"p75":118225.0,"p90":127562.0},"fail_mix":[]}],"meta":{"source":"DVSA anonymised MOT results & failure items (OGL v3.0); DVSA Recalls; VCA CO₂/MPG; GOV.UK VED","version":"weekly"}}