{"make":"LAND ROVER","model":"RANGE ROVER EVOQUE SE AUTO","make_slug":"land-rover","model_slug":"range-rover-evoque-se-auto","first_reg_year":2020,"fuels":[],"co2_panel":[],"recalls":[],"mot_curve":[{"age":3,"tests":null,"pass_rate":0.983,"mileage":{"p50":21283.0,"p75":25385.0,"p90":26178.0},"fail_mix":[]},{"age":4,"tests":null,"pass_rate":1.0,"mileage":{"p50":39556.0,"p75":39556.0,"p90":39556.0},"fail_mix":[]}],"meta":{"source":"DVSA anonymised MOT results & failure items (OGL v3.0); DVSA Recalls; VCA CO₂/MPG; GOV.UK VED","version":"weekly"}}