{"make":"TESLA","model":"ROADSTER","make_slug":"tesla","model_slug":"roadster","first_reg_year":2011,"fuels":[],"co2_panel":[],"recalls":[],"mot_curve":[{"age":12,"tests":null,"pass_rate":1.0,"mileage":{"p50":22894.0,"p75":22894.0,"p90":22894.0},"fail_mix":[]},{"age":13,"tests":null,"pass_rate":1.0,"mileage":{"p50":39266.0,"p75":39266.0,"p90":39266.0},"fail_mix":[]}],"meta":{"source":"DVSA anonymised MOT results & failure items (OGL v3.0); DVSA Recalls; VCA CO₂/MPG; GOV.UK VED","version":"weekly"}}