{"make":"VAUXHALL","model":"GRANDLAND X GRIFFIN ED T D","make_slug":"vauxhall","model_slug":"grandland-x-griffin-ed-t-d","first_reg_year":2021,"fuels":[],"co2_panel":[],"recalls":[],"mot_curve":[{"age":2,"tests":null,"pass_rate":0.941,"mileage":{"p50":35846.0,"p75":42830.0,"p90":42830.0},"fail_mix":[]},{"age":3,"tests":null,"pass_rate":1.0,"mileage":{"p50":45545.0,"p75":45545.0,"p90":45545.0},"fail_mix":[]}],"meta":{"source":"DVSA anonymised MOT results & failure items (OGL v3.0); DVSA Recalls; VCA CO₂/MPG; GOV.UK VED","version":"weekly"}}