{"make":"MAZDA","model":"CX-30 GT SPORT TECH MHEV 4X4","make_slug":"mazda","model_slug":"cx-30-gt-sport-tech-mhev-4x4","first_reg_year":2021,"fuels":[],"co2_panel":[],"recalls":[],"mot_curve":[{"age":2,"tests":null,"pass_rate":0.93,"mileage":{"p50":17972.0,"p75":29402.0,"p90":30698.0},"fail_mix":[]},{"age":3,"tests":null,"pass_rate":1.0,"mileage":{"p50":18198.0,"p75":23846.0,"p90":27446.0},"fail_mix":[]}],"meta":{"source":"DVSA anonymised MOT results & failure items (OGL v3.0); DVSA Recalls; VCA CO₂/MPG; GOV.UK VED","version":"weekly"}}