{"make":"MINI","model":"COOPER GRAPHITE","make_slug":"mini","model_slug":"cooper-graphite","first_reg_year":2010,"fuels":[],"co2_panel":[],"recalls":[],"mot_curve":[{"age":13,"tests":null,"pass_rate":1.0,"mileage":{"p50":107955.0,"p75":107955.0,"p90":107955.0},"fail_mix":[]},{"age":14,"tests":null,"pass_rate":1.0,"mileage":{"p50":94157.0,"p75":94157.0,"p90":94157.0},"fail_mix":[]}],"meta":{"source":"DVSA anonymised MOT results & failure items (OGL v3.0); DVSA Recalls; VCA CO₂/MPG; GOV.UK VED","version":"weekly"}}