{"make":"FORD","model":"TOURNEO CUSTOM 320 T-NIUM MHEV","make_slug":"ford","model_slug":"tourneo-custom-320-t-nium-mhev","first_reg_year":2023,"fuels":[],"co2_panel":[],"recalls":[],"mot_curve":[{"age":0,"tests":null,"pass_rate":1.0,"mileage":{"p50":38150.0,"p75":56608.0,"p90":67683.0},"fail_mix":[]},{"age":1,"tests":null,"pass_rate":1.0,"mileage":{"p50":43003.0,"p75":43003.0,"p90":43003.0},"fail_mix":[]}],"meta":{"source":"DVSA anonymised MOT results & failure items (OGL v3.0); DVSA Recalls; VCA CO₂/MPG; GOV.UK VED","version":"weekly"}}