{"make":"MOTO GUZZI","model":"V7 III SPECIAL","make_slug":"moto-guzzi","model_slug":"v7-iii-special","first_reg_year":2017,"fuels":[],"co2_panel":[],"recalls":[],"mot_curve":[{"age":6,"tests":null,"pass_rate":0.5,"mileage":{"p50":11046.0,"p75":12167.0,"p90":12840.0},"fail_mix":[]},{"age":7,"tests":null,"pass_rate":1.0,"mileage":{"p50":5123.0,"p75":6474.0,"p90":7285.0},"fail_mix":[]}],"meta":{"source":"DVSA anonymised MOT results & failure items (OGL v3.0); DVSA Recalls; VCA CO₂/MPG; GOV.UK VED","version":"weekly"}}