{"make":"MERCEDES-BENZ","model":"VITO 119 SPORT CDI AUTO","make_slug":"mercedes-benz","model_slug":"vito-119-sport-cdi-auto","first_reg_year":2021,"fuels":[],"co2_panel":[],"recalls":[],"mot_curve":[{"age":2,"tests":null,"pass_rate":0.775,"mileage":{"p50":35935.0,"p75":63969.0,"p90":71482.0},"fail_mix":[]},{"age":3,"tests":null,"pass_rate":0.9,"mileage":{"p50":34275.0,"p75":43842.0,"p90":59218.0},"fail_mix":[]}],"meta":{"source":"DVSA anonymised MOT results & failure items (OGL v3.0); DVSA Recalls; VCA CO₂/MPG; GOV.UK VED","version":"weekly"}}