{"make":"JAGUAR","model":"E-TYPE","make_slug":"jaguar","model_slug":"e-type","first_reg_year":1969,"fuels":[],"co2_panel":[],"recalls":[],"mot_curve":[{"age":54,"tests":null,"pass_rate":1.0,"mileage":{"p50":78021.0,"p75":78319.0,"p90":93540.0},"fail_mix":[]},{"age":55,"tests":null,"pass_rate":1.0,"mileage":{"p50":43322.0,"p75":43322.0,"p90":43322.0},"fail_mix":[]}],"meta":{"source":"DVSA anonymised MOT results & failure items (OGL v3.0); DVSA Recalls; VCA CO₂/MPG; GOV.UK VED","version":"weekly"}}