{"make":"SMART (MCC)","model":"CITY COUPE","make_slug":"smart-mcc","model_slug":"city-coupe","first_reg_year":2010,"fuels":[],"co2_panel":[],"recalls":[],"mot_curve":[{"age":13,"tests":null,"pass_rate":0.667,"mileage":{"p50":65735.0,"p75":73737.0,"p90":95729.0},"fail_mix":[]},{"age":14,"tests":null,"pass_rate":0.857,"mileage":{"p50":66111.0,"p75":77969.0,"p90":81205.0},"fail_mix":[]}],"meta":{"source":"DVSA anonymised MOT results & failure items (OGL v3.0); DVSA Recalls; VCA CO₂/MPG; GOV.UK VED","version":"weekly"}}