{"make":"NISSAN","model":"NV250 ACENTA DCI","make_slug":"nissan","model_slug":"nv250-acenta-dci","first_reg_year":2020,"fuels":[],"co2_panel":[],"recalls":[],"mot_curve":[{"age":3,"tests":null,"pass_rate":0.882,"mileage":{"p50":63607.0,"p75":73856.0,"p90":193957.0},"fail_mix":[]},{"age":4,"tests":null,"pass_rate":1.0,"mileage":{"p50":26926.0,"p75":31240.0,"p90":33828.0},"fail_mix":[]}],"meta":{"source":"DVSA anonymised MOT results & failure items (OGL v3.0); DVSA Recalls; VCA CO₂/MPG; GOV.UK VED","version":"weekly"}}