{"make":"HONDA","model":"CRF 1100 D4-L","make_slug":"honda","model_slug":"crf-1100-d4-l","first_reg_year":2021,"fuels":[],"co2_panel":[],"recalls":[],"mot_curve":[{"age":2,"tests":null,"pass_rate":1.0,"mileage":{"p50":3740.0,"p75":3740.0,"p90":5295.0},"fail_mix":[]},{"age":3,"tests":null,"pass_rate":1.0,"mileage":{"p50":5130.0,"p75":7436.0,"p90":8820.0},"fail_mix":[]}],"meta":{"source":"DVSA anonymised MOT results & failure items (OGL v3.0); DVSA Recalls; VCA CO₂/MPG; GOV.UK VED","version":"weekly"}}