{"make":"AUDI","model":"A6","make_slug":"audi","model_slug":"a6","first_reg_year":2008,"fuels":[],"co2_panel":[],"recalls":[],"mot_curve":[{"age":15,"tests":null,"pass_rate":0.708,"mileage":{"p50":149604.0,"p75":177736.0,"p90":208029.0},"fail_mix":[]},{"age":16,"tests":null,"pass_rate":0.752,"mileage":{"p50":155522.0,"p75":186499.0,"p90":214957.0},"fail_mix":[]}],"meta":{"source":"DVSA anonymised MOT results & failure items (OGL v3.0); DVSA Recalls; VCA CO₂/MPG; GOV.UK VED","version":"weekly"}}