{"make":"NISSAN","model":"PICKUP","make_slug":"nissan","model_slug":"pickup","first_reg_year":2002,"fuels":[],"co2_panel":[],"recalls":[],"mot_curve":[{"age":21,"tests":null,"pass_rate":0.643,"mileage":{"p50":116496.0,"p75":131595.0,"p90":140768.0},"fail_mix":[]},{"age":22,"tests":null,"pass_rate":0.6,"mileage":{"p50":82093.0,"p75":122480.0,"p90":122480.0},"fail_mix":[]}],"meta":{"source":"DVSA anonymised MOT results & failure items (OGL v3.0); DVSA Recalls; VCA CO₂/MPG; GOV.UK VED","version":"weekly"}}