{"make":"VOLKSWAGEN","model":"EOS","make_slug":"volkswagen","model_slug":"eos","first_reg_year":2007,"fuels":[],"co2_panel":[],"recalls":[],"mot_curve":[{"age":16,"tests":null,"pass_rate":0.676,"mileage":{"p50":101807.0,"p75":127958.0,"p90":155536.0},"fail_mix":[]},{"age":17,"tests":null,"pass_rate":0.763,"mileage":{"p50":100366.0,"p75":118847.0,"p90":134413.0},"fail_mix":[]}],"meta":{"source":"DVSA anonymised MOT results & failure items (OGL v3.0); DVSA Recalls; VCA CO₂/MPG; GOV.UK VED","version":"weekly"}}