{"make":"NISSAN","model":"NOTE","make_slug":"nissan","model_slug":"note","first_reg_year":2015,"fuels":[],"co2_panel":[],"recalls":[],"mot_curve":[{"age":8,"tests":null,"pass_rate":0.84,"mileage":{"p50":50143.0,"p75":69954.0,"p90":89373.0},"fail_mix":[]},{"age":9,"tests":null,"pass_rate":0.802,"mileage":{"p50":55537.0,"p75":75921.0,"p90":96310.0},"fail_mix":[]}],"meta":{"source":"DVSA anonymised MOT results & failure items (OGL v3.0); DVSA Recalls; VCA CO₂/MPG; GOV.UK VED","version":"weekly"}}