{"make":"RENAULT","model":"MEGANE","make_slug":"renault","model_slug":"megane","first_reg_year":2017,"fuels":[],"co2_panel":[],"recalls":[],"mot_curve":[{"age":6,"tests":null,"pass_rate":0.827,"mileage":{"p50":55833.0,"p75":71729.0,"p90":94255.0},"fail_mix":[]},{"age":7,"tests":null,"pass_rate":0.824,"mileage":{"p50":53115.0,"p75":67674.0,"p90":97981.0},"fail_mix":[]}],"meta":{"source":"DVSA anonymised MOT results & failure items (OGL v3.0); DVSA Recalls; VCA CO₂/MPG; GOV.UK VED","version":"weekly"}}