{"make":"VAUXHALL","model":"MOKKA","make_slug":"vauxhall","model_slug":"mokka","first_reg_year":2018,"fuels":[],"co2_panel":[],"recalls":[],"mot_curve":[{"age":5,"tests":null,"pass_rate":0.817,"mileage":{"p50":37984.0,"p75":50113.0,"p90":61980.0},"fail_mix":[]},{"age":6,"tests":null,"pass_rate":0.807,"mileage":{"p50":41431.0,"p75":54727.0,"p90":66213.0},"fail_mix":[]}],"meta":{"source":"DVSA anonymised MOT results & failure items (OGL v3.0); DVSA Recalls; VCA CO₂/MPG; GOV.UK VED","version":"weekly"}}