{"make":"VOLKSWAGEN","model":"KOMBI","make_slug":"volkswagen","model_slug":"kombi","first_reg_year":2010,"fuels":[],"co2_panel":[],"recalls":[],"mot_curve":[{"age":13,"tests":null,"pass_rate":0.5,"mileage":{"p50":43621.0,"p75":43621.0,"p90":43621.0},"fail_mix":[]},{"age":14,"tests":null,"pass_rate":0.5,"mileage":{"p50":92175.0,"p75":92175.0,"p90":92175.0},"fail_mix":[]}],"meta":{"source":"DVSA anonymised MOT results & failure items (OGL v3.0); DVSA Recalls; VCA CO₂/MPG; GOV.UK VED","version":"weekly"}}