{"make":"TRIUMPH","model":"STREET","make_slug":"triumph","model_slug":"street","first_reg_year":2016,"fuels":[],"co2_panel":[],"recalls":[],"mot_curve":[{"age":7,"tests":null,"pass_rate":0.75,"mileage":{"p50":6572.0,"p75":6846.0,"p90":7341.0},"fail_mix":[]},{"age":8,"tests":null,"pass_rate":0.667,"mileage":{"p50":5707.0,"p75":6120.0,"p90":6367.0},"fail_mix":[]}],"meta":{"source":"DVSA anonymised MOT results & failure items (OGL v3.0); DVSA Recalls; VCA CO₂/MPG; GOV.UK VED","version":"weekly"}}