{"make":"FIAT","model":"DUCATO 35 MULTIJET II AUTO","make_slug":"fiat","model_slug":"ducato-35-multijet-ii-auto","first_reg_year":2021,"fuels":[],"co2_panel":[],"recalls":[],"mot_curve":[{"age":2,"tests":null,"pass_rate":0.556,"mileage":{"p50":72591.0,"p75":94736.0,"p90":99737.0},"fail_mix":[]},{"age":3,"tests":null,"pass_rate":0.667,"mileage":{"p50":80681.0,"p75":94330.0,"p90":102520.0},"fail_mix":[]}],"meta":{"source":"DVSA anonymised MOT results & failure items (OGL v3.0); DVSA Recalls; VCA CO₂/MPG; GOV.UK VED","version":"weekly"}}