{"make":"CITROEN","model":"DISPATCH 1400 DRIVER BHDI S/S","make_slug":"citroen","model_slug":"dispatch-1400-driver-bhdi-s-s","first_reg_year":2021,"fuels":[],"co2_panel":[],"recalls":[],"mot_curve":[{"age":2,"tests":null,"pass_rate":0.786,"mileage":{"p50":38150.0,"p75":60764.0,"p90":65721.0},"fail_mix":[]},{"age":3,"tests":null,"pass_rate":0.8,"mileage":{"p50":46637.0,"p75":53624.0,"p90":90868.0},"fail_mix":[]}],"meta":{"source":"DVSA anonymised MOT results & failure items (OGL v3.0); DVSA Recalls; VCA CO₂/MPG; GOV.UK VED","version":"weekly"}}